Metadata-Version: 2.1
Name: facial-emotion-recognition
Version: 0.3.3
Summary: It recognize facial emotions from the image
Home-page: UNKNOWN
Author: Rayyan Akhtar
Author-email: akhtar.rayyan@live.com
License: MIT
Platform: UNKNOWN
Classifier: Programming Language :: Python :: 3
Classifier: Programming Language :: Python :: 3.6
Classifier: Programming Language :: Python :: 3.7
